teradatagenai/LICENSE-3RD-PARTY.pdf
teradatagenai/LICENSE.pdf
teradatagenai/README.md
teradatagenai/__init__.py
teradatagenai/_version.py
teradatagenai/common/__init__.py
teradatagenai/common/constants.py
teradatagenai/common/exceptions.py
teradatagenai/common/message_codes.py
teradatagenai/common/messages.py
teradatagenai/common/utils.py
teradatagenai/common/version_config.py
teradatagenai/example-data/LLM_handbook.pdf
teradatagenai/example-data/SQL_Fundamentals.pdf
teradatagenai/example-data/amazon_example.json
teradatagenai/example-data/amazon_review_query.csv
teradatagenai/example-data/amazon_reviews_10.csv
teradatagenai/example-data/amazon_reviews_25.csv
teradatagenai/example-data/amazon_reviews_embedded.csv
teradatagenai/example-data/amazon_reviews_embedded_10_alter.csv
teradatagenai/example-data/analyze_sentiment.py
teradatagenai/example-data/byom_example.json
teradatagenai/example-data/classify_text.py
teradatagenai/example-data/context_data.csv
teradatagenai/example-data/context_example.json
teradatagenai/example-data/detect_language.py
teradatagenai/example-data/embeddings.py
teradatagenai/example-data/employee_data.csv
teradatagenai/example-data/employee_example.json
teradatagenai/example-data/entity_recognition.py
teradatagenai/example-data/extract_key_phrases.py
teradatagenai/example-data/mask_pii.py
teradatagenai/example-data/question_data.csv
teradatagenai/example-data/question_example.json
teradatagenai/example-data/recognize_pii.py
teradatagenai/example-data/sentence_similarity.py
teradatagenai/example-data/summarize_text.py
teradatagenai/example-data/td_gen_ai_env_template.json
teradatagenai/example-data/td_sample_embeddings_script_02.py
teradatagenai/example-data/td_sample_embeddings_script_03.py
teradatagenai/example-data/td_sample_inference_script_02.py
teradatagenai/example-data/td_sample_inference_script_03.py
teradatagenai/garbage_collector/__init__.py
teradatagenai/garbage_collector/garbage_collector.py
teradatagenai/llm/__init__.py
teradatagenai-20.0.0.5.dist-info/METADATA
teradatagenai-20.0.0.5.dist-info/WHEEL
teradatagenai-20.0.0.5.dist-info/top_level.txt
teradatagenai-20.0.0.5.dist-info/zip-safe
teradatagenai-20.0.0.5.dist-info/RECORD
