Metadata-Version: 2.1
Name: teradatagenai
Version: 20.0.0.5
Summary: Teradata package for Generative-AI powered text analytics on Teradata Vantage
Home-page: https://teradata.com
Author: Teradata Corporation
License: Teradata License Agreement
Keywords: Teradata
Platform: MacOS X, Windows, Linux
Classifier: Programming Language :: Python :: 3 :: Only
Classifier: Programming Language :: Python :: 3.9
Classifier: Operating System :: Microsoft :: Windows
Classifier: Operating System :: MacOS :: MacOS X
Classifier: Operating System :: POSIX :: Linux
Classifier: Topic :: Database :: Front-Ends
Classifier: License :: Other/Proprietary License
Requires-Python: >=3.9
Requires-Dist: teradataml (>=20.00.00.08)
Provides-Extra: nv-ingest-client
Requires-Dist: nv-ingest-client ; extra == 'nv-ingest-client'
